orrnob_drops_automation/__init__.py
orrnob_drops_automation/base.py
orrnob_drops_automation-0.1.6.dist-info/LICENCE
orrnob_drops_automation-0.1.6.dist-info/METADATA
orrnob_drops_automation-0.1.6.dist-info/WHEEL
orrnob_drops_automation-0.1.6.dist-info/top_level.txt
orrnob_drops_automation-0.1.6.dist-info/RECORD
