Metadata-Version: 2.1
Name: orrnob_drops_automation
Version: 0.1.6
Summary: A package for airdrop automation.
Home-page: https://github.com/OrrnobMahmud/Orrnob-Drops-Automation
Author: Orrnob Mahmud
Author-email: orrnobmahmud@gmail.com
Project-URL: Website, https://www.orrnobmahmud.com
Classifier: Programming Language :: Python :: 3
Classifier: License :: OSI Approved :: MIT License
Classifier: Operating System :: OS Independent
Requires-Python: >=3.6
License-File: LICENCE
Requires-Dist: colorama
Requires-Dist: requests
Requires-Dist: brotli
